aiofilecache.py
aiofilecache-0.0.1.dist-info/DESCRIPTION.rst
aiofilecache-0.0.1.dist-info/LICENSE.txt
aiofilecache-0.0.1.dist-info/METADATA
aiofilecache-0.0.1.dist-info/RECORD
aiofilecache-0.0.1.dist-info/WHEEL
aiofilecache-0.0.1.dist-info/metadata.json
aiofilecache-0.0.1.dist-info/top_level.txt
