Metadata-Version: 2.0
Name: aiofilecache
Version: 0.0.1
Summary: File backend for aiocache
Home-page: http://github.com/Suor/aioscrape
Author: Alexander Schepanovski
Author-email: suor.web@gmail.com
License: BSD
Platform: UNKNOWN
Classifier: Development Status :: 4 - Beta
Classifier: License :: OSI Approved :: BSD License
Classifier: Operating System :: OS Independent
Classifier: Programming Language :: Python
Classifier: Programming Language :: Python :: 3
Classifier: Programming Language :: Python :: 3.6
Classifier: Programming Language :: Python :: Implementation :: CPython
Classifier: Topic :: Software Development :: Libraries :: Python Modules
Classifier: Intended Audience :: Developers
Requires-Dist: aiocache
Requires-Dist: aiofiles
